.gitignore
.pre-commit-config.yaml
LICENSE.md
MANIFEST.in
README.md
requirements.txt
setup.cfg
setup.py
version.py
.github/workflows/pythonapp.yml
chiscore/__init__.py
chiscore/_davies.py
chiscore/_liu.py
chiscore/_optimal.py
chiscore/_testit.py
chiscore.egg-info/PKG-INFO
chiscore.egg-info/SOURCES.txt
chiscore.egg-info/dependency_links.txt
chiscore.egg-info/requires.txt
chiscore.egg-info/top_level.txt
chiscore.egg-info/zip-safe
chiscore/_data/__init__.py
chiscore/_data/_files.py
chiscore/_data/bound.npz
chiscore/_data/danilo_nan.npz
chiscore/_data/davies_pvalue.npz
chiscore/_data/inf.npz
chiscore/_data/optimal_davies_pvalue.npz
chiscore/test/__init__.py
chiscore/test/test_davies.py
chiscore/test/test_liu.py
chiscore/test/test_optimal.py
chiscore/test/test_pval.py