Metadata-Version: 2.1
Name: chiscore
Version: 0.2.3
Summary: Test statistics from linear combination of chi-squared distributions.
Home-page: https://github.com/limix/chiscore
Author: Rachel Moore, Danilo Horta
Author-email: rm18@sanger.ac.uk, horta@ebi.ac.uk
Maintainer: Danilo Horta
Maintainer-email: horta@ebi.ac.uk
License: MIT
Download-URL: https://github.com/limix/chiscore
Keywords: test statistic,chi-squared distribution,p-value
Platform: Windows
Platform: MacOS
Platform: Linux
Classifier: Development Status :: 5 - Production/Stable
Classifier: License :: OSI Approved :: MIT License
Classifier: Operating System :: OS Independent
Classifier: Programming Language :: Python
